{
    "1": [
        {
            "id": 81,
            "template": "MAGNEMITE_NORMAL",
            "form": 655
        },
        {
            "id": 403,
            "template": "SHINX"
        },
        {
            "id": 436,
            "template": "BRONZOR"
        },
        {
            "id": 532,
            "template": "TIMBURR"
        },
        {
            "id": 677,
            "template": "ESPURR"
        }
    ],
    "3": [
        {
            "id": 256,
            "template": "COMBUSKEN_NORMAL",
            "form": 1361
        },
        {
            "id": 303,
            "template": "MAWILE_NORMAL",
            "form": 833
        },
        {
            "id": 375,
            "template": "METANG_NORMAL",
            "form": 767
        },
        {
            "id": 621,
            "template": "DRUDDIGON"
        }
    ],
    "5": [
        {
            "id": 379,
            "template": "REGISTEEL"
        }
    ],
    "6": [
        {
            "id": 229,
            "template": "HOUNDOOM_NORMAL",
            "form": 232,
            "temp_evolution_id": 1
        }
    ]
}