{
    "1": [
        {
            "id": 46,
            "template": "PARAS"
        },
        {
            "id": 201,
            "template": "UNOWN_T",
            "form": 20
        },
        {
            "id": 204,
            "template": "PINECO_NORMAL",
            "form": 1244
        },
        {
            "id": 511,
            "template": "PANSAGE"
        },
        {
            "id": 595,
            "template": "JOLTIK"
        }
    ],
    "3": [
        {
            "id": 49,
            "template": "VENOMOTH_NORMAL",
            "form": 262
        },
        {
            "id": 127,
            "template": "PINSIR_NORMAL",
            "form": 898
        },
        {
            "id": 205,
            "template": "FORRETRESS_NORMAL",
            "form": 1247
        },
        {
            "id": 213,
            "template": "SHUCKLE_NORMAL",
            "form": 827
        }
    ],
    "5": [
        {
            "id": 649,
            "template": "GENESECT_CHILL",
            "form": 596
        }
    ],
    "6": [
        {
            "id": 212,
            "template": "SCIZOR_NORMAL",
            "form": 250,
            "temp_evolution_id": 1
        }
    ]
}