{
    "1": [
        {
            "id": 201,
            "template": "UNOWN_S",
            "form": 19
        },
        {
            "id": 215,
            "template": "SNEASEL_NORMAL",
            "form": 797
        },
        {
            "id": 315,
            "template": "ROSELIA"
        },
        {
            "id": 403,
            "template": "SHINX"
        },
        {
            "id": 515,
            "template": "PANPOUR"
        }
    ],
    "3": [
        {
            "id": 113,
            "template": "CHANSEY"
        },
        {
            "id": 176,
            "template": "TOGETIC"
        },
        {
            "id": 281,
            "template": "KIRLIA_NORMAL",
            "form": 295
        },
        {
            "id": 340,
            "template": "WHISCASH"
        }
    ],
    "5": [
        {
            "id": 484,
            "template": "PALKIA"
        }
    ],
    "6": [
        {
            "id": 460,
            "template": "ABOMASNOW_NORMAL",
            "form": 935,
            "temp_evolution_id": 1
        }
    ]
}